colalamo/__init__.py
colalamo/colalamo.py
colalamo/config.py
colalamo/shtoken.py
colalamo-0.1.2106.dist-info/METADATA
colalamo-0.1.2106.dist-info/WHEEL
colalamo-0.1.2106.dist-info/entry_points.txt
colalamo-0.1.2106.dist-info/top_level.txt
colalamo-0.1.2106.dist-info/RECORD
